ftp_receiver/__init__.py
ftp_receiver/config.py
ftp_receiver/consumer.py
ftp_receiver/ftp_client.py
ftp_receiver/main.py
ftp_receiver/publisher.py
ftp_receiver/version.py
py_ftp_receiver-0.0.4.dist-info/METADATA
py_ftp_receiver-0.0.4.dist-info/WHEEL
py_ftp_receiver-0.0.4.dist-info/entry_points.txt
py_ftp_receiver-0.0.4.dist-info/top_level.txt
py_ftp_receiver-0.0.4.dist-info/RECORD
